bmcds/__init__.py
bmcds/bmcds.py
bmcds/classification.py
bmcds/cli.py
bmcds/eda.py
bmcds/functions.py
bmcds/regression.py
bmcds/time_series_modeling.py
bmcds/time_series_modeling_old.py
bmcds-0.1.2.dist-info/AUTHORS.rst
bmcds-0.1.2.dist-info/LICENSE
bmcds-0.1.2.dist-info/METADATA
bmcds-0.1.2.dist-info/WHEEL
bmcds-0.1.2.dist-info/entry_points.txt
bmcds-0.1.2.dist-info/top_level.txt
bmcds-0.1.2.dist-info/RECORD
