Metadata-Version: 2.1
Name: bmcds
Version: 0.1.2
Summary: Collection of personal functions for data science
Home-page: https://github.com/BenJMcCarty/bmcds
Author: Ben McCarty
Author-email: bmccarty505@gmail.com
License: GNU General Public License v3
Keywords: bmcds
Platform: UNKNOWN
Classifier: Development Status :: 2 - Pre-Alpha
Classifier: Intended Audience :: Developers
Classifier: License :: OSI Approved :: GNU General Public License v3 (GPLv3)
Classifier: Natural Language :: English
Classifier: Programming Language :: Python :: 3
Classifier: Programming Language :: Python :: 3.6
Classifier: Programming Language :: Python :: 3.7
Classifier: Programming Language :: Python :: 3.8
Requires-Python: >=3.6
License-File: LICENSE
License-File: AUTHORS.rst
Requires-Dist: Click (>=7.0)
Requires-Dist: pmdarima
